cdklabs/aws_data_solutions_framework/__init__.py
cdklabs/aws_data_solutions_framework/py.typed
cdklabs/aws_data_solutions_framework/_jsii/__init__.py
cdklabs/aws_data_solutions_framework/_jsii/aws-data-solutions-framework@1.21.3.jsii.tgz
cdklabs/aws_data_solutions_framework/consumption/__init__.py
cdklabs/aws_data_solutions_framework/governance/__init__.py
cdklabs/aws_data_solutions_framework/processing/__init__.py
cdklabs/aws_data_solutions_framework/storage/__init__.py
cdklabs/aws_data_solutions_framework/streaming/__init__.py
cdklabs/aws_data_solutions_framework/utils/__init__.py
cdklabs.aws_data_solutions_framework-1.21.3.dist-info/LICENSE
cdklabs.aws_data_solutions_framework-1.21.3.dist-info/METADATA
cdklabs.aws_data_solutions_framework-1.21.3.dist-info/WHEEL
cdklabs.aws_data_solutions_framework-1.21.3.dist-info/top_level.txt
cdklabs.aws_data_solutions_framework-1.21.3.dist-info/RECORD
