Metadata-Version: 2.1
Name: cdklabs.aws_data_solutions_framework
Version: 1.21.3
Summary: L3 CDK Constructs used to build data solutions with AWS
Home-page: https://awslabs.github.io/data-solutions-framework-on-aws/
Author: Amazon Web Services
License: Apache-2.0
Project-URL: Source, https://github.com/awslabs/data-solutions-framework-on-aws.git
Classifier: Intended Audience :: Developers
Classifier: Operating System :: OS Independent
Classifier: Programming Language :: JavaScript
Classifier: Programming Language :: Python :: 3 :: Only
Classifier: Programming Language :: Python :: 3.8
Classifier: Programming Language :: Python :: 3.9
Classifier: Programming Language :: Python :: 3.10
Classifier: Programming Language :: Python :: 3.11
Classifier: Typing :: Typed
Classifier: Development Status :: 5 - Production/Stable
Classifier: License :: OSI Approved
Requires-Python: ~=3.8
License-File: LICENSE
Requires-Dist: aws-cdk-lib<3.0.0,>=2.208.0
Requires-Dist: aws-cdk.lambda-layer-kubectl-v33<3.0.0,>=2.0.0
Requires-Dist: constructs<11.0.0,>=10.4.2
Requires-Dist: jsii<2.0.0,>=1.106.0
Requires-Dist: publication>=0.0.3
Requires-Dist: typeguard<4.3.0,>=2.13.3
